README.md
setup.py
isu_tool/__init__.py
isu_tool.egg-info/PKG-INFO
isu_tool.egg-info/SOURCES.txt
isu_tool.egg-info/dependency_links.txt
isu_tool.egg-info/not-zip-safe
isu_tool.egg-info/top_level.txt
isu_tool/algorithm/__init__.py
isu_tool/algorithm/algorithm.py
isu_tool/ui/__init__.py
isu_tool/ui/ui.py