Metadata-Version: 1.0
Name: isu-tool
Version: 0.1.1
Summary: Many useful tools for computer scientists!
Home-page: https://github.com/waylight3/isu_tool
Author: DoHyeon Lee
Author-email: waylight3@naver.com
License: MIT
Keywords: isu,tool,isu_tool,ui,algorithm
Platform: UNKNOWN
